[
  {
    "id": 1,
    "type": "Email",
    "description": "Our friendly team is here to help.",
    "value": "photoeditspecialist@gmail.com",
    "icon": "GoMail"
  },
  {
    "id": 2,
    "type": "Office",
    "description": "Come say hello at our office HQ.",
    "value": "Gaibandha,Rangpur,Bangladesh.",
    "icon": "GoLocation"
  },
  {
    "id": 3,
    "type": "Phone",
    "description": "Mon-Sat: 08:00 to 17:00 (24-hour format)", 
    "value": "+8801897677943",
    "icon": "IoCallOutline"
  }
]